[
    {
        "id": "86bbf50e.a7f188",
        "type": "tab",
        "label": "doors",
        "disabled": false,
        "info": ""
    },
    {
        "id": "2046730f.81897c",
        "type": "debug",
        "z": "86bbf50e.a7f188",
        "name": "received",
        "active": true,
        "tosidebar": true,
        "console": false,
        "tostatus": false,
        "complete": "payload",
        "targetType": "msg",
        "statusVal": "",
        "statusType": "auto",
        "x": 540,
        "y": 120,
        "wires": []
    },
    {
        "id": "7317e0e6.862af",
        "type": "inject",
        "z": "86bbf50e.a7f188",
        "name": "test",
        "props": [
            {
                "p": "payload"
            },
            {
                "p": "topic",
                "vt": "str"
            }
        ],
        "repeat": "",
        "crontab": "",
        "once": false,
        "onceDelay": 0.1,
        "topic": "",
        "payload": "{ \"deviceId\": 405419896, \"door\":1 }",
        "payloadType": "json",
        "x": 130,
        "y": 120,
        "wires": [
            [
                "bedb99cc.cc0768"
            ]
        ]
    },
    {
        "id": "bedb99cc.cc0768",
        "type": "get-door-control",
        "z": "86bbf50e.a7f188",
        "name": "get-door-control",
        "config": "cbd92359.dbf19",
        "x": 320,
        "y": 120,
        "wires": [
            [
                "2046730f.81897c",
                "ed5427f.86328d8",
                "e6a2598d.e7f958"
            ]
        ]
    },
    {
        "id": "6d8d48f7.397bb8",
        "type": "set-door-control",
        "z": "86bbf50e.a7f188",
        "name": "set-door-control",
        "config": "cbd92359.dbf19",
        "x": 320,
        "y": 280,
        "wires": [
            [
                "552b0a9d.9bc984",
                "742df092.553a2",
                "6ef964a9.7c2b4c"
            ]
        ]
    },
    {
        "id": "552b0a9d.9bc984",
        "type": "debug",
        "z": "86bbf50e.a7f188",
        "name": "received",
        "active": true,
        "tosidebar": true,
        "console": false,
        "tostatus": false,
        "complete": "payload",
        "targetType": "msg",
        "statusVal": "",
        "statusType": "auto",
        "x": 540,
        "y": 280,
        "wires": []
    },
    {
        "id": "5fb4202c.0de66",
        "type": "inject",
        "z": "86bbf50e.a7f188",
        "name": "test",
        "props": [
            {
                "p": "payload"
            }
        ],
        "repeat": "",
        "crontab": "",
        "once": false,
        "onceDelay": 0.1,
        "topic": "",
        "payload": "{\"deviceId\":405419896,\"door\":1,\"delay\":6,\"control\":\"normally closed\"}",
        "payloadType": "json",
        "x": 130,
        "y": 280,
        "wires": [
            [
                "6d8d48f7.397bb8"
            ]
        ]
    },
    {
        "id": "6c1b3177.30bd2",
        "type": "open-door",
        "z": "86bbf50e.a7f188",
        "name": "open-door",
        "config": "cbd92359.dbf19",
        "x": 310,
        "y": 440,
        "wires": [
            [
                "cf49a18d.73b92",
                "e35ca985.ab1a28"
            ]
        ]
    },
    {
        "id": "cf49a18d.73b92",
        "type": "debug",
        "z": "86bbf50e.a7f188",
        "name": "received",
        "active": true,
        "tosidebar": true,
        "console": false,
        "tostatus": false,
        "complete": "payload",
        "targetType": "msg",
        "statusVal": "",
        "statusType": "auto",
        "x": 540,
        "y": 440,
        "wires": []
    },
    {
        "id": "23ed32e1.98a00e",
        "type": "inject",
        "z": "86bbf50e.a7f188",
        "name": "test",
        "props": [
            {
                "p": "payload"
            }
        ],
        "repeat": "",
        "crontab": "",
        "once": false,
        "onceDelay": 0.1,
        "topic": "",
        "payload": "{ \"deviceId\":405419896, \"door\":1 }",
        "payloadType": "json",
        "x": 130,
        "y": 440,
        "wires": [
            [
                "6c1b3177.30bd2"
            ]
        ]
    },
    {
        "id": "ed5427f.86328d8",
        "type": "debug",
        "z": "86bbf50e.a7f188",
        "name": "door-1.delay",
        "active": true,
        "tosidebar": true,
        "console": false,
        "tostatus": false,
        "complete": "payload.doorControlState.delay",
        "targetType": "msg",
        "statusVal": "",
        "statusType": "auto",
        "x": 550,
        "y": 160,
        "wires": []
    },
    {
        "id": "e6a2598d.e7f958",
        "type": "debug",
        "z": "86bbf50e.a7f188",
        "name": "door-1.control",
        "active": true,
        "tosidebar": true,
        "console": false,
        "tostatus": false,
        "complete": "payload.doorControlState.control.state",
        "targetType": "msg",
        "statusVal": "",
        "statusType": "auto",
        "x": 560,
        "y": 200,
        "wires": []
    },
    {
        "id": "742df092.553a2",
        "type": "debug",
        "z": "86bbf50e.a7f188",
        "name": "door-1.delay",
        "active": true,
        "tosidebar": true,
        "console": false,
        "tostatus": false,
        "complete": "payload.doorControlState.delay",
        "targetType": "msg",
        "statusVal": "",
        "statusType": "auto",
        "x": 550,
        "y": 320,
        "wires": []
    },
    {
        "id": "6ef964a9.7c2b4c",
        "type": "debug",
        "z": "86bbf50e.a7f188",
        "name": "door-1.control",
        "active": true,
        "tosidebar": true,
        "console": false,
        "tostatus": false,
        "complete": "payload.doorControlState.control.state",
        "targetType": "msg",
        "statusVal": "",
        "statusType": "auto",
        "x": 560,
        "y": 360,
        "wires": []
    },
    {
        "id": "e35ca985.ab1a28",
        "type": "debug",
        "z": "86bbf50e.a7f188",
        "name": "door-1.opened",
        "active": true,
        "tosidebar": true,
        "console": false,
        "tostatus": false,
        "complete": "payload.opened",
        "targetType": "msg",
        "statusVal": "",
        "statusType": "auto",
        "x": 560,
        "y": 480,
        "wires": []
    },
    {
        "id": "cbd92359.dbf19",
        "type": "config",
        "z": "",
        "name": "demo",
        "timeout": "5000",
        "bind": "192.168.1.100",
        "broadcast": "192.168.1.255:60000",
        "listen": "192.168.1.100:60001",
        "controllers": "{\"303986753\":{\"address\":\"192.168.1.100:60000\"},\"405419896\":{\"address\":\"192.168.1.100:60000\"}}",
        "debug": true
    }
]